{
  "id": "5ac7b59b-b5f6-4364-abe0-900dd1e2425c",
  "prevId": "efe38e03-74ae-4122-be0f-2a04303cf457",
  "version": "6",
  "dialect": "postgresql",
  "tables": {
    "public.migration_meta": {
      "name": "migration_meta",
      "schema": "",
      "columns": {
        "id": {
          "name": "id",
          "type": "varchar(255)",
          "primaryKey": true,
          "notNull": true
        },
        "meta_key": {
          "name": "meta_key",
          "type": "text",
          "primaryKey": false,
          "notNull": true
        },
        "meta_value": {
          "name": "meta_value",
          "type": "text",
          "primaryKey": false,
          "notNull": false
        },
        "created_at": {
          "name": "created_at",
          "type": "timestamp with time zone",
          "primaryKey": false,
          "notNull": true,
          "default": "now()"
        },
        "updated_at": {
          "name": "updated_at",
          "type": "timestamp with time zone",
          "primaryKey": false,
          "notNull": true,
          "default": "now()"
        }
      },
      "indexes": {},
      "foreignKeys": {},
      "compositePrimaryKeys": {},
      "uniqueConstraints": {
        "migration_meta_meta_key_unique": {
          "name": "migration_meta_meta_key_unique",
          "nullsNotDistinct": false,
          "columns": [
            "meta_key"
          ]
        }
      }
    },
    "public.upload": {
      "name": "upload",
      "schema": "",
      "columns": {
        "id": {
          "name": "id",
          "type": "varchar(255)",
          "primaryKey": true,
          "notNull": true
        },
        "status": {
          "name": "status",
          "type": "varchar(50)",
          "primaryKey": false,
          "notNull": true,
          "default": "'pending'"
        },
        "key": {
          "name": "key",
          "type": "varchar(1024)",
          "primaryKey": false,
          "notNull": true
        },
        "capability": {
          "name": "capability",
          "type": "varchar(255)",
          "primaryKey": false,
          "notNull": true
        },
        "entity_id": {
          "name": "entity_id",
          "type": "varchar(255)",
          "primaryKey": false,
          "notNull": false
        },
        "expires_at": {
          "name": "expires_at",
          "type": "timestamp with time zone",
          "primaryKey": false,
          "notNull": true
        },
        "created_at": {
          "name": "created_at",
          "type": "timestamp with time zone",
          "primaryKey": false,
          "notNull": true,
          "default": "now()"
        },
        "updated_at": {
          "name": "updated_at",
          "type": "timestamp with time zone",
          "primaryKey": false,
          "notNull": true,
          "default": "now()"
        }
      },
      "indexes": {},
      "foreignKeys": {},
      "compositePrimaryKeys": {},
      "uniqueConstraints": {
        "upload_key_unique": {
          "name": "upload_key_unique",
          "nullsNotDistinct": false,
          "columns": [
            "key"
          ]
        }
      }
    }
  },
  "enums": {},
  "schemas": {},
  "_meta": {
    "columns": {},
    "schemas": {},
    "tables": {}
  }
}